sanic_secure_session/__init__.py
sanic_secure_session/session.py
sanic_secure_session-0.2.1.dist-info/DESCRIPTION.rst
sanic_secure_session-0.2.1.dist-info/METADATA
sanic_secure_session-0.2.1.dist-info/RECORD
sanic_secure_session-0.2.1.dist-info/WHEEL
sanic_secure_session-0.2.1.dist-info/metadata.json
sanic_secure_session-0.2.1.dist-info/top_level.txt
