Metadata-Version: 2.0
Name: sanic-secure-session
Version: 0.2.1
Summary: A server-side secure sessions plugin for Sanic
Home-page: https://github.com/saabeilin/sanic-secure-session
Author: Sergei Beilin
Author-email: saabeilin@gmail.com
License: MIT license
Keywords: sanic,session
Platform: UNKNOWN
Classifier: Development Status :: 3 - Alpha
Classifier: Intended Audience :: Developers
Classifier: License :: OSI Approved :: MIT License
Classifier: Operating System :: Unix
Classifier: Operating System :: POSIX
Classifier: Operating System :: Microsoft :: Windows
Classifier: Programming Language :: Python
Classifier: Programming Language :: Python :: 3
Classifier: Programming Language :: Python :: 3.5
Classifier: Programming Language :: Python :: 3.6
Classifier: Programming Language :: Python :: Implementation :: CPython
Classifier: Programming Language :: Python :: Implementation :: PyPy
Classifier: Topic :: Utilities
Requires-Dist: sanic
Requires-Dist: itsdangerous
